dp_translation/__init__.py
dp_translation/key_logic.py
dp_translation/model_mixin.py
dp_translation/models.py
dp_translation-1.0.0.dist-info/LICENSE
dp_translation-1.0.0.dist-info/METADATA
dp_translation-1.0.0.dist-info/WHEEL
dp_translation-1.0.0.dist-info/top_level.txt
dp_translation-1.0.0.dist-info/RECORD
