Metadata-Version: 2.1
Name: dp-translation
Version: 1.0.0
Summary: Utilities to retrieve general .json files and more specifically jsonschema files
Home-page: https://github.com/dataPuzzler/dp_translation
Author: Lukas Seppelfricke
Author-email: data.puzzler@gmail.com
License: UNKNOWN
Keywords: translation,i18n
Platform: UNKNOWN
Classifier: Development Status :: 5 - Production/Stable
Classifier: Intended Audience :: Developers
Classifier: Topic :: Software Development :: Libraries
Classifier: License :: OSI Approved :: BSD License
Classifier: Programming Language :: Python :: 3
Requires-Python: >=3.7, <4
Requires-Dist: sqlalchemy (>=1.4)
Requires-Dist: dp-sqlalchemy-wrapper (>=2.3)
